okapy/__init__.py
okapy/corpus_maker.py
okapy/datamuse.py
okapy/intent_target_analysis.py
okapy/math.py
okapy/oplsa.py
okapy/scrap.py
okapy/sutils.py
okapy/term_stats.py
okapy/term_stats_maker.py
okapy/termstats.py
okapy/text_processors.py
okapy/wordnet_explorer.py
okapy/words_api.py
okapy/tests/__init__.py
okapy/tests/termstats.py
okapy-0.0.1.dist-info/LICENSE
okapy-0.0.1.dist-info/METADATA
okapy-0.0.1.dist-info/WHEEL
okapy-0.0.1.dist-info/top_level.txt
okapy-0.0.1.dist-info/RECORD
