Metadata-Version: 2.1
Name: okapy
Version: 0.0.1
Summary: NLP toolset
Home-page: https://github.com/thorwhalen/ut/tree/master/okapy
Author: Thor Whalen
License: mit
Platform: any
